dtintegrations/__init__.py
dtintegrations/outputs.py
dtintegrations/provider.py
dtintegrations/request.py
dtintegrations/data_connector/__init__.py
dtintegrations/data_connector/http_push.py
dtintegrations/data_connector/metadata.py
dtintegrations-0.6.1.dist-info/LICENSE
dtintegrations-0.6.1.dist-info/METADATA
dtintegrations-0.6.1.dist-info/WHEEL
dtintegrations-0.6.1.dist-info/top_level.txt
dtintegrations-0.6.1.dist-info/RECORD
