Metadata-Version: 2.1
Name: dtintegrations
Version: 0.6.1
Summary: Disruptive Technologies Python Integrations.
Home-page: https://github.com/disruptive-technologies/disruptive-dataconnector
Author: Disruptive Technologies Research AS
Author-email: developer-support@disruptive-technologies.com
Keywords: disruptive,technologies,dt,integration,api
Classifier: Natural Language :: English
Classifier: License :: OSI Approved :: MIT License
Classifier: Development Status :: 3 - Alpha
Classifier: Intended Audience :: Developers
Classifier: Programming Language :: Python :: 3.8
Classifier: Programming Language :: Python :: 3.9
Classifier: Programming Language :: Python :: 3.10
Classifier: Programming Language :: Python :: 3.11
Classifier: Operating System :: OS Independent
Requires-Python: >=3.8
License-File: LICENSE
Requires-Dist: disruptive >=1.6.0
Provides-Extra: dev
Requires-Dist: setuptools >=54.2.0 ; extra == 'dev'
Requires-Dist: wheel >=0.36.2 ; extra == 'dev'
Requires-Dist: pytest >=6.2.2 ; extra == 'dev'
Requires-Dist: pytest-mock >=3.5.1 ; extra == 'dev'
Requires-Dist: pytest-cov >=2.11.1 ; extra == 'dev'
Requires-Dist: mypy >=0.812 ; extra == 'dev'
Requires-Dist: flake8 >=3.9.0 ; extra == 'dev'
